pyneb/__init__.py
pyneb/atomic_data/3he_ii_atom_cloudy.dat
pyneb/atomic_data/3he_ii_coll_cloudy.dat
pyneb/atomic_data/al_ii_atom_JSP86-HK87-VVF96-KS86.dat
pyneb/atomic_data/al_ii_coll_KHAF92-TBK85-TBK84.dat
pyneb/atomic_data/al_viii_coll_MBZ20.dat
pyneb/atomic_data/ar_ii_atom_Bal06.dat
pyneb/atomic_data/ar_ii_coll_PB95.dat
pyneb/atomic_data/ar_iii_atom_M83-KS86.dat
pyneb/atomic_data/ar_iii_atom_MB09.dat
pyneb/atomic_data/ar_iii_atom_MZ83.dat
pyneb/atomic_data/ar_iii_coll_GMZ95.dat
pyneb/atomic_data/ar_iii_coll_MB09.dat
pyneb/atomic_data/ar_iv_atom_CK63.dat
pyneb/atomic_data/ar_iv_atom_Fal99.dat
pyneb/atomic_data/ar_iv_atom_MZ82.dat
pyneb/atomic_data/ar_iv_atom_MZ82a-KS86.dat
pyneb/atomic_data/ar_iv_atom_RGJ19.dat
pyneb/atomic_data/ar_iv_coll_M83.dat
pyneb/atomic_data/ar_iv_coll_RB97.dat
pyneb/atomic_data/ar_iv_coll_ZBL87.dat
pyneb/atomic_data/ar_v_atom_LL93-MZ82-KS86.dat
pyneb/atomic_data/ar_v_coll_GMZ95.dat
pyneb/atomic_data/ba_ii_atom_C04.dat
pyneb/atomic_data/ba_ii_coll_SB98.dat
pyneb/atomic_data/ba_iv_atom_BHQZ95.dat
pyneb/atomic_data/ba_iv_coll_SB98.dat
pyneb/atomic_data/br_iii_atom_BH86.dat
pyneb/atomic_data/br_iii_coll_S97.dat
pyneb/atomic_data/br_iv_atom_BH86.dat
pyneb/atomic_data/br_iv_coll_S97.dat
pyneb/atomic_data/br_v_atom_M18.dat
pyneb/atomic_data/br_v_coll_M18.dat
pyneb/atomic_data/c_i_atom_FFS85.dat
pyneb/atomic_data/c_i_coll_JBK87-PA76.dat
pyneb/atomic_data/c_i_rec_P91.func
pyneb/atomic_data/c_ii_atom_GMZ98.dat
pyneb/atomic_data/c_ii_coll_BHKD05.dat
pyneb/atomic_data/c_ii_coll_BP92.dat
pyneb/atomic_data/c_ii_coll_LR77.dat
pyneb/atomic_data/c_ii_rec_D00.func
pyneb/atomic_data/c_ii_rec_P91.func
pyneb/atomic_data/c_iii_atom_G83-NS78-WFD96.dat
pyneb/atomic_data/c_iii_atom_TFF99-NS78.dat
pyneb/atomic_data/c_iii_atom_U-NS78.dat
pyneb/atomic_data/c_iii_coll_Bal85.dat
pyneb/atomic_data/c_iii_coll_Bal85extrap.dat
pyneb/atomic_data/c_iii_coll_KFB92-Bal85extrap.dat
pyneb/atomic_data/c_iii_rec_P91.func
pyneb/atomic_data/c_iv_atom_WFD96.dat
pyneb-1.1.28.dist-info/licenses/LICENSE.md
pyneb-1.1.28.dist-info/METADATA
pyneb-1.1.28.dist-info/WHEEL
pyneb-1.1.28.dist-info/top_level.txt
pyneb-1.1.28.dist-info/RECORD
