Metadata-Version: 2.4
Name: pyneb
Version: 1.1.28
Summary: A Python package for nebular analysis
Author: Valentina Luridiana
Author-email: Christophe Morisset <chris.morisset@gmail.com>
Project-URL: Homepage, http://www.iac.es/proyecto/PyNeb/
Project-URL: Repository, https://github.com/Morisset/PyNeb_devel
Project-URL: Documentation, http://morisset.github.io/PyNeb_devel/
Project-URL: Changelog, https://github.com/Morisset/PyNeb_devel/tree/master/docs/CHANGES
Keywords: nebular,analysis,astronomy
Requires-Python: >=3.8
License-File: LICENSE.md
Requires-Dist: numpy
Requires-Dist: matplotlib
Requires-Dist: scipy
Requires-Dist: h5py
Requires-Dist: astropy
Dynamic: license-file
